CHANGES.txt
LICENSE.txt
MANIFEST.in
README.rst
setup.py
djed.static.egg-info/PKG-INFO
djed.static.egg-info/SOURCES.txt
djed.static.egg-info/dependency_links.txt
djed.static.egg-info/requires.txt
djed.static.egg-info/top_level.txt
djed/static/__init__.py
djed/static/jspm.py
docs/Makefile
docs/api.rst
docs/changes.rst
docs/conf.py
docs/configuration.rst
docs/getting-started.rst
docs/index.rst
docs/local-components.rst
docs/multiple-components.rst
docs/support.rst
docs/_build/doctrees/api.doctree
docs/_build/doctrees/changes.doctree
docs/_build/doctrees/configuration.doctree
docs/_build/doctrees/environment.pickle
docs/_build/doctrees/getting-started.doctree
docs/_build/doctrees/index.doctree
docs/_build/doctrees/local-components.doctree
docs/_build/doctrees/multiple-components.doctree
docs/_build/doctrees/support.doctree
docs/_build/html/.buildinfo
docs/_build/html/api.html
docs/_build/html/changes.html
docs/_build/html/configuration.html
docs/_build/html/genindex.html
docs/_build/html/getting-started.html
docs/_build/html/index.html
docs/_build/html/local-components.html
docs/_build/html/multiple-components.html
docs/_build/html/objects.inv
docs/_build/html/py-modindex.html
docs/_build/html/search.html
docs/_build/html/searchindex.js
docs/_build/html/support.html
docs/_build/html/_modules/index.html
docs/_build/html/_modules/djed/static.html
docs/_build/html/_sources/api.txt
docs/_build/html/_sources/changes.txt
docs/_build/html/_sources/configuration.txt
docs/_build/html/_sources/getting-started.txt
docs/_build/html/_sources/index.txt
docs/_build/html/_sources/local-components.txt
docs/_build/html/_sources/multiple-components.txt
docs/_build/html/_sources/support.txt
docs/_build/html/_static/ajax-loader.gif
docs/_build/html/_static/basic.css
docs/_build/html/_static/comment-bright.png
docs/_build/html/_static/comment-close.png
docs/_build/html/_static/comment.png
docs/_build/html/_static/doctools.js
docs/_build/html/_static/down-pressed.png
docs/_build/html/_static/down.png
docs/_build/html/_static/file.png
docs/_build/html/_static/jquery-1.11.1.js
docs/_build/html/_static/jquery.js
docs/_build/html/_static/minus.png
