Metadata-Version: 1.1
Name: djed.static
Version: 0.5
Summary: Integration of BowerStatic into Pyramid for managing static resources with Bower
Home-page: https://github.com/djedproject/djed.static
Author: Djed developers
Author-email: djedproject@googlegroups.com
License: ISC License (ISCL)
Keywords: djed pyramid pylons bower static bowerstatic
Platform: UNKNOWN
Classifier: Framework :: Pyramid
Classifier: Intended Audience :: Developers
Classifier: License :: OSI Approved :: ISC License (ISCL)
Classifier: Programming Language :: Python :: 3
Classifier: Programming Language :: Python :: 3.3
Classifier: Programming Language :: Python :: 3.4
Classifier: Programming Language :: Python :: 3.5
Classifier: Topic :: Internet :: WWW/HTTP
